{
  "siteTitle": "EnergySHR Marketplace",
  "siteTagline": "Solving energy transition challenges",
  "siteUrl": "https://portal.minimal-gaia-x.eu",
  "siteImage": "/share.png",
  "copyright": "All Rights Reserved.",
  "menu": [
    {
      "name": "About",
      "link": "/about"
    },
    {
      "name": "Catalogue",
      "link": "/search"
    },
    {
      "name": "Publish",
      "link": "/publish"
    },
    {
      "name": "Profile",
      "link": "/profile"
    }
  ],
  "announcement": "",
  "warning": {
    "ctd": "Please note that Compute-to-Data is still in alpha phase."
  },
  "footer": {
    "designedBy": "",
    "partners": "Centre for Energy System Intelligence",
    "links": [
      { "label": "About this demo", "link": "/about" },
      { "label": "About Gaia-X", "link": "/gaia-x" },
      {
        "label": "Catalogue",
        "link": "/search"
      },
      { "label": "First time visiting", "link": "/onboarding" }
    ]
  }
}
